setup.py
tictoc/__init__.py
tictoc/tic_toc_toe.py
tictoc_vanithas.egg-info/PKG-INFO
tictoc_vanithas.egg-info/SOURCES.txt
tictoc_vanithas.egg-info/dependency_links.txt
tictoc_vanithas.egg-info/not-zip-safe
tictoc_vanithas.egg-info/top_level.txt