Metadata-Version: 1.0
Name: tictoc-vanithas
Version: 2.0
Summary: Tic-Toc-Toe Game
Home-page: UNKNOWN
Author: UNKNOWN
Author-email: UNKNOWN
License: UNKNOWN
Platform: UNKNOWN
